{
  //"type": "flying",
  "flying": true,
  "databaseTag": "09cyclant-strengthened-unit",
  "lowAltitude": true,
  "accel": 0.06,
  "speed": 1.4,
  "drag": 0.02,
  "health": 45000,//38000
  "armor": 22,
  "rotateSpeed": 1.3,
  "research": {
    "parent": "magnetic",
    "objectives": [ "assemble-selector1","ultra-assembler" ],
    "requirements": [ "silicon/20000","fibralt/9000","surge-alloy/7500","phase-fabric/5000","silicide/2000" ]
  },
  "researchCostMultiplier": 0.01,
  "hitSize": 72,
  "engineSize": 11,
  "engineOffset": 40.5,
  "targetFlags": [ "generator","turret" ],
  "itemCapacity": 500,
  "deathSound": "si2ExplodeLoud",
  "immunities": [ "burning","melting","freezing","frozen" ],
  "lightColor": "ffa665",
  "shownPlanets": [ "cyclant","phoon","maress","thavina" ],
  "engines": [
    {
      "x": 38,
      "y": -32,
      "rotation": -45,
      "radius": 7
    },
    {
      "x": -38,
      "y": -32,
      "rotation": -135,
      "radius": 7
    },
    {
      "x": 32,
      "y": -41,
      "rotation": -90,
      "radius": 5
    },
    {
      "x": -32,
      "y": -41,
      "rotation": -90,
      "radius": 5
    }
  ],
  "weapons": [
    {
      "name": "corona-launcher"
      "x": 22.25,
      "y": -14.75,
      "rotate": true,
      "top": true,
      "rotateSpeed": 2.5,
      "shadow": 30,
      "shootSound": "shootTank",
      "shake": 4,
      "reload": 55,
      "cooldownTime": 45,
      "recoil": 4,
      "ejectEffect": "none",
      "shootY": 21.75,
      "shoot": {
        "shots": 4,
        "shotDelay": 1
      },
      "inaccuracy": 4,
      "velocityRnd": 0.3,
      "bullet": {
        "weaveScale": 5,
        "weaveMag": 2,
        "damage": 150,
        "pierce": true,
        "pierceCap": 10,
        "pierceBuilding": true,
        "trailColor": "ffa665",
        "trailLength": 10,
        "trailWidth": 1.5,
        "hitSize": 8,
        "width": 10,
        "height": 15,
        "shrinkY": 0,
        "sprite": "circle-bullet",
        "frontColor": "ffffff",
        "backColor": "ffa665",
        "spin": 8,
        "trailInterval": 1,
        "speed": 5.7,
        "lifetime": 78,
        "lightColor": "ffa665",
        "shootEffect": {
          "type": "MultiEffect",
          "effects": [
            "blastExplosion",
            "shootTitan"
            {
              "type": "ParticleEffect",
              "particles": 12,
              "lifetime": 90,
              "sizeFrom": 8,
              "sizeTo": 0,
              "colorFrom": "ffa66588",
              "colorTo": "d06b5333",
              "length": 20,
              "baseLength": 3,
              "cone": 5,
              "interp": "circleOut"
            }
          ]
        },
        "hitSound": "explosion",
        "hitShake": 1,
        "hitEffect": "flakExplosion",
        "fragBullets": 3,
        "fragOnHit": true,
        "fragVelocityMin": 0.5,
        "fragLifeMin": 0.5,
        "fragBullet": {
          "lifetime": 45,
          "width": 16,
          "height": 16,
          "spin": 5,
          "speed": 4,
          "drag": 0.05,
          "collides": false,
          "splashDamage": 40,
          "splashDamageRadius": 24,
          "hitEffect": "none",
          "despawnEffect": "blastExplosion",
          "despawnShake": 2,
          "despawnSound": "explosion",
          "frontColor": "ffa665",
          "backColor": "d06b53",
          "status": "blasted",
          "statusDuration": 60
        },
        "hittable": false,
        "despawnEffect": {
          "type": "MultiEffect",
          "effects": [
            "launchPod",
            {
              "type": "ParticleEffect",
              "particles": 10,
              "lifetime": 180,
              "sizeFrom": 13,
              "sizeTo": 0,
              "colorFrom": "ffa66566",
              "colorTo": "d06b5355",
              "length": 48,
              "baseLength": 0,
              "interp": "circleOut",
              "sizeInterp": "circleOut"
            }
          ]
        },
        "splashDamageRadius": 24,
        "splashDamage": 20,
        "despawnShake": 5,
        "despawnSound": "roFlyingBombExplode",
        "status": "blasted",
        "statusDuration": 60,
        "keepVelocity": false,
        /*"despawnBullets": [
          {
  "instantDisappear": true,
  "hitEffect": "none",
  "despawnEffect": "none",
  "splashDamage": 217,
  "splashDamageRadius": 48,
  "status": "blasted",
  "statusDuration": 60,
  "collides": false,
  "breakable": false
          }
        ]*/
      }
    },
    {
      "name": "corona-melter",
      "x": 30.5,
      "y": 5.25,
      "layerOffset": -0.01,
      "shootY": 18.5,
      "shootX": -1.5,
      "reload": 40,
      "alternate": false,
      "cooldownTime": 55,
      "recoilTime": 30,
      "rotateSpeed": 2,
      "rotationLimit": 270,
      "shootCone": 45,
      "ejectEffect": "none",
      "recoil": 1,
      "rotate": true,
      "shake": 4,
      "shootSound": "beamMeltdown",
      "initialShootSound": "shootBeamPlasmaSmall",
      "continuous": true,
      "bullet": {
        "type": "ContinuousLaserBulletType",
        "damage": 40,
        "length": 280,
        "drawSize": 800,
        "lifetime": 120,
        "shake": 1,
        "despawnEffect": "smokeCloud",
        "smokeEffect": "none",
        "incendChance": 0.1,
        "incendSpread": 5,
        "incendAmount": 1,
        "width": 5,
        "makeFire": true,
        "colors": [ "d06b5333","ffa66580","ffa665","ffffff" ],
        "status": "melting",
        "statusDuration": 300,
        "knockback": 1,
        "hitSize": 3,
        "lightColor": "ffa665"
      }
    },
    {
      "name": "corona-shooter",
      "x": 0,
      "mirror": false,
      "y": -21.75,
      "rotate": true,
      "top": true,
      "shadow": 12,
      "rotateSpeed": 5,
      "shootCone": 30,
      "reload": 8,
      "recoil": 1,
      "recoilTime": 36,
      "cooldownTime": 36,
      "shootY": 9.25,
      "shoot": { 
        "type": "ShootAlternate",
        "spread": 7
      },
      "shootSound": "shootCyclone",
      "ejectEffect": "casing3",
      "velocityRnd": 0.1,
      "inaccuracy": 1,
      "bullet": {
        "width": 12,
        "height": 16,
        "frontColor": "ffa665",
        "backColor": "d06b53",
        "shrinkY": 0,
        "speed": 7,
        "lifetime": 53,
        "damage": 23,
        "knockback": 0.3,
        "hitEffect": "hitBulletBig",
        "despawnEffect": "hitBulletBig",
        "shootEffect": "shootBig",
        "smokeEffect": "shootBigSmoke",
        "lightColor": "ffa665"
      }
    },
    {
      "name": "corona-shooter",
      "x": 0,
      "mirror": false,
      "y": 12.25,
      "rotate": true,
      "top": true,
      "shadow": 12,
      "rotateSpeed": 5,
      "shootCone": 30,
      "reload": 8,
      "recoil": 1,
      "recoilTime": 36,
      "cooldownTime": 36,
      "shootY": 9.25,
      "shoot": { 
        "type": "ShootAlternate",
        "spread": 7
      },
      "shootSound": "shootCyclone",
      "ejectEffect": "casing3",
      "velocityRnd": 0.1,
      "inaccuracy": 1,
      "bullet": {
        "width": 12,
        "height": 16,
        "frontColor": "ffa665",
        "backColor": "d06b53",
        "shrinkY": 0,
        "speed": 7,
        "lifetime": 53,
        "damage": 23,
        "knockback": 0.3,
        "hitEffect": "hitBulletBig",
        "despawnEffect": "hitBulletBig",
        "shootEffect": "shootBig",
        "smokeEffect": "shootBigSmoke",
        "lightColor": "ffa665"
      }
    },
    {
      "reload": 1800,
      "useAttackRange": false,
      "x": 0,
      "y": -38,
      "baseRotation": 180,
      "rotate": false,
      "mirror": false,
      "shootCone": 44,
      "shootSound": "shootQuad",
      "ejectEffect": "none",
      "noAttack": false,
      "bullet": {
        "recoil": 0.8,
        "type": "BombBulletType",
        "keepVelocity": false,
        "maxRange": 40,
        "sprite": "missile-large",
        "shootEffect": {
          "type": "WaveEffect",
          "sides": 24,
          "sizeFrom": 10,
          "sizeTo": 20,
          "strokeFrom": 20,
          "strokeTo": 0,
          "colorTo": "ffa665",
          "colorFrom": "ffa665",
          "lifetime": 15
        },
        "smokeEffect": "none",
        "width": 26,
        "height": 26,
        "speed": 2,
        "drag": 0.03,
        "shrinkY": 0.2,
        "hitEffect": "impactReactorExplosion",
        "despawnEffect": "none",
        "backColor": "d06b53",
        "frontColor": "ffa665",
        "reflectable": false,
        "hitSound": "explosionReactor",
        "despawnSound": "explosionReactor",
        "splashDamage": 7600,
        "scaledSplashDamage": false,
        "splashDamageRadius": 144,
        "splashDamagePierce": true,
        "collidesAir": true,
        "lifetime": 80,
        "shrinkX": 0.2,
        "hitShake": 13,
        "despawnShake": 13,
        "lightColor": "ffa665"
      },
      "useAttackRange": false
    }
  ]
}